hashid_field/__init__.py
hashid_field/conf.py
hashid_field/descriptor.py
hashid_field/field.py
hashid_field/hashid.py
hashid_field/lookups.py
hashid_field/rest.py
hashid_field/validators.py
django_hashid_field-3.4.1.dist-info/LICENSE
django_hashid_field-3.4.1.dist-info/METADATA
django_hashid_field-3.4.1.dist-info/WHEEL
django_hashid_field-3.4.1.dist-info/top_level.txt
django_hashid_field-3.4.1.dist-info/RECORD
