Metadata-Version: 2.1
Name: django-hashid-field
Version: 3.4.1
Summary: A Hashids obfuscated Django Model Field
Home-page: https://github.com/nshafer/django-hashid-field
Author: Nathan Shafer
Author-email: nate-pypi@lotech.org
License: MIT
Keywords: django hashids hashid
Classifier: Development Status :: 5 - Production/Stable
Classifier: Intended Audience :: Developers
Classifier: License :: OSI Approved :: MIT License
Classifier: Programming Language :: Python :: 3
Classifier: Programming Language :: Python :: 3.7
Classifier: Programming Language :: Python :: 3.8
Classifier: Programming Language :: Python :: 3.9
Classifier: Programming Language :: Python :: 3.10
Classifier: Programming Language :: Python :: 3.11
Classifier: Framework :: Django
Classifier: Framework :: Django :: 3.2
Classifier: Framework :: Django :: 4.2
Classifier: Framework :: Django :: 5.0
License-File: LICENSE
